hbase/__init__.py
hbase/admin.py
hbase/delete.py
hbase/get.py
hbase/put.py
hbase/rest_client.py
hbase/scan.py
hbase/scan_filter_helper.py
hbase/utils.py
hbase/test/__init__.py
hbase/test/integration_test.py
hbase/test/messages_example.py
hbase/test/test_admin.py
hbase/test/test_delete.py
hbase/test/test_get.py
hbase/test/test_put.py
hbase/test/test_rest_client.py
hbase/test/test_scan.py
hbase/test/test_utils.py
hbase_rest_py-1.0.0.dist-info/LICENSE
hbase_rest_py-1.0.0.dist-info/METADATA
hbase_rest_py-1.0.0.dist-info/WHEEL
hbase_rest_py-1.0.0.dist-info/top_level.txt
hbase_rest_py-1.0.0.dist-info/RECORD
