Metadata-Version: 2.1
Name: hbase-rest-py
Version: 1.0.0
Summary: HBase client based on HBase REST
Home-page: https://github.com/samirMoP/hbase-rest-py
Author: Samir Ahmic
Author-email: ahmic.samir@gmail.com
License: UNKNOWN
Project-URL: Bug Tracker, https://github.com/samirMoP/hbase-rest-py/issues
Platform: UNKNOWN
Classifier: Programming Language :: Python :: 3
Classifier: License :: OSI Approved :: Apache Software License
Classifier: Operating System :: OS Independent
Requires-Python: >=3.6
License-File: LICENSE
Requires-Dist: requests
Requires-Dist: requests-toolbelt
